vscrapy/cmdline.py
vscrapy/scrapy.cfg
vscrapy/vscrapy/__init__.py
vscrapy/vscrapy/middlewares.py
vscrapy/vscrapy/pipelines.py
vscrapy/vscrapy/settings.py
vscrapy/vscrapy/scrapy_mod/_retry.py
vscrapy/vscrapy/scrapy_mod/redis_corestats.py
vscrapy/vscrapy/scrapy_mod/redis_statscollectors.py
vscrapy/vscrapy/scrapy_redis_mod/__init__.py
vscrapy/vscrapy/scrapy_redis_mod/_reqser.py
vscrapy/vscrapy/scrapy_redis_mod/connection.py
vscrapy/vscrapy/scrapy_redis_mod/defaults.py
vscrapy/vscrapy/scrapy_redis_mod/dupefilter.py
vscrapy/vscrapy/scrapy_redis_mod/picklecompat.py
vscrapy/vscrapy/scrapy_redis_mod/pipelines.py
vscrapy/vscrapy/scrapy_redis_mod/queue.py
vscrapy/vscrapy/scrapy_redis_mod/scheduler.py
vscrapy/vscrapy/scrapy_redis_mod/spiders.py
vscrapy/vscrapy/scrapy_redis_mod/utils.py
vscrapy/vscrapy/spiders/__init__.py
vscrapy/vscrapy/spiders/vspider.py
vscrapy-1.0.8.dist-info/LICENSE
vscrapy-1.0.8.dist-info/METADATA
vscrapy-1.0.8.dist-info/WHEEL
vscrapy-1.0.8.dist-info/entry_points.txt
vscrapy-1.0.8.dist-info/top_level.txt
vscrapy-1.0.8.dist-info/RECORD
