Metadata-Version: 2.1
Name: vscrapy
Version: 1.0.8
Summary: multi task scrapy redis.
Home-page: https://github.com/cilame/vscrapy
Author: cilame
Author-email: opaquism@hotmail.com
License: MIT
Platform: UNKNOWN
Classifier: Environment :: Web Environment
Classifier: Intended Audience :: Developers
Classifier: Operating System :: OS Independent
Requires-Python: >=3.6
Requires-Dist: Scrapy (>=1.0)
Requires-Dist: redis (>=2.10)
Requires-Dist: six (>=1.5.2)
